sonosrestapi/__init__.py
sonosrestapi/audioclip.py
sonosrestapi/favourite.py
sonosrestapi/group.py
sonosrestapi/houshold.py
sonosrestapi/music_serve_account.py
sonosrestapi/my_sonos.py
sonosrestapi/player.py
sonosrestapi/playlist.py
sonosrestapi/session.py
sonosrestapi-0.0.6.dist-info/LICENSE.txt
sonosrestapi-0.0.6.dist-info/METADATA
sonosrestapi-0.0.6.dist-info/WHEEL
sonosrestapi-0.0.6.dist-info/top_level.txt
sonosrestapi-0.0.6.dist-info/RECORD
