Metadata-Version: 2.1
Name: sonosrestapi
Version: 0.0.6
Summary: sonos rest api wrapper
Home-page: https://github.com/faqnet/sonos-rest-api-wrapper
Author: Fagnet
Author-email: robin.schoch@fhnw.ch
License: MIT
Download-URL: https://github.com/faqnet/sonos-rest-api-wrapper/archive/0.0.4.tar.gz
Keywords: sonos
Platform: UNKNOWN
Classifier: Development Status :: 3 - Alpha
Classifier: Intended Audience :: Developers
Classifier: Topic :: Software Development :: Build Tools
Classifier: License :: OSI Approved :: MIT License
Classifier: Programming Language :: Python :: 3
Classifier: Programming Language :: Python :: 3.4
Classifier: Programming Language :: Python :: 3.5
Classifier: Programming Language :: Python :: 3.6
Requires-Dist: typing
Requires-Dist: requests
